CodeTrace-0.0.3.data/scripts/ct
codetrace/__init__.py
codetrace/code_insert.py
codetrace/codetrace.py
codetrace/test_ct.py
CodeTrace-0.0.3.dist-info/METADATA
CodeTrace-0.0.3.dist-info/WHEEL
CodeTrace-0.0.3.dist-info/top_level.txt
CodeTrace-0.0.3.dist-info/RECORD
