Metadata-Version: 2.1
Name: CodeTrace
Version: 0.0.3
Summary: Trace your python code in a simply way
Home-page: https://github.com/ranchlai/CodeTrace
Author: Lai Yongquan
Author-email: ranchlai@163.com
License: UNKNOWN
Platform: UNKNOWN
Classifier: Programming Language :: Python :: 3
Classifier: License :: OSI Approved :: MIT License
Classifier: Operating System :: OS Independent
Requires-Python: >=3.6
